{
  "packageId": "io.github.chun1025.being",
  "host": "chun1025.github.io",
  "name": "Being",
  "launcherName": "Being",
  "display": "standalone",
  "orientation": "portrait",
  "themeColor": "#F5A623",
  "navigationColor": "#000000",
  "navigationColorDark": "#000000",
  "navigationDividerColor": "#000000",
  "navigationDividerColorDark": "#000000",
  "backgroundColor": "#1a1a1a",
  "enableNotifications": false,
  "startUrl": "/my-life-app/",
  "iconUrl": "https://chun1025.github.io/my-life-app/icon-512.png",
  "maskableIconUrl": "https://chun1025.github.io/my-life-app/icon-512.png",
  "monochromeIconUrl": "https://chun1025.github.io/my-life-app/icon-512.png",
  "appVersion": "1",
  "appVersionCode": 1,
  "signingKey": {
    "path": "android.keystore",
    "alias": "android"
  },
  "splashScreenFadeOutDuration": 300,
  "enableSiteSettingsShortcut": true,
  "isChromeOSOnly": false,
  "isMetaQuest": false,
  "fullScopeUrl": "https://chun1025.github.io/my-life-app/",
  "minSdkVersion": 19,
  "webManifestUrl": "https://chun1025.github.io/my-life-app/manifest.json",
  "generatorApp": "bubblewrap-cli",
  "shortcuts": []
}
